README.txt
setup.cfg
setup.py
SWMM5_EA.egg-info/PKG-INFO
SWMM5_EA.egg-info/SOURCES.txt
SWMM5_EA.egg-info/dependency_links.txt
SWMM5_EA.egg-info/top_level.txt
swmm5ea/about_dialog.py
swmm5ea/about_dialog_.py
swmm5ea/mainwindow.py
swmm5ea/mainwindow_.py
swmm5ea/metadata.py
swmm5ea/parameters_dialog.py
swmm5ea/parameters_dialog_.py
swmm5ea/pyratemp.py
swmm5ea/res_rc.py
swmm5ea/slotdiff.py
swmm5ea/swmm5ea_tests.py
swmm5ea/swmm5ec.py
swmm5ea/swmm_ea_controller.py
swmm5ea/swmm_ea_temp_data.py
swmm5ea/swmmeaproject.py
swmm5ea/swmmedit_dialog.py
swmm5ea/swmmedit_dialog_.py
swmm5ea/tee_test.py
swmm5ea/customcode/README.txt
swmm5ea/doc/_build/doctrees/Calibration of Networks.doctree
swmm5ea/doc/_build/doctrees/Introduction.doctree
swmm5ea/doc/_build/doctrees/Quick Start.doctree
swmm5ea/doc/_build/doctrees/SWMM5-EA User Interface.doctree
swmm5ea/doc/_build/doctrees/Simple Optimization.doctree
swmm5ea/doc/_build/doctrees/Staged Optimization.doctree
swmm5ea/doc/_build/doctrees/Working Principles.doctree
swmm5ea/doc/_build/doctrees/environment.pickle
swmm5ea/doc/_build/doctrees/index.doctree
swmm5ea/doc/_build/html/.buildinfo
swmm5ea/doc/_build/html/Calibration of Networks.html
swmm5ea/doc/_build/html/Introduction.html
swmm5ea/doc/_build/html/Quick Start.html
swmm5ea/doc/_build/html/SWMM5-EA User Interface.html
swmm5ea/doc/_build/html/Simple Optimization.html
swmm5ea/doc/_build/html/Staged Optimization.html
swmm5ea/doc/_build/html/Working Principles.html
swmm5ea/doc/_build/html/genindex.html
swmm5ea/doc/_build/html/html.zip
swmm5ea/doc/_build/html/index.html
swmm5ea/doc/_build/html/objects.inv
swmm5ea/doc/_build/html/search.html
swmm5ea/doc/_build/html/searchindex.js
swmm5ea/doc/_build/html/_images/calibration_g0.png
swmm5ea/doc/_build/html/_images/calibration_g1.png
swmm5ea/doc/_build/html/_images/calibration_g2.png
swmm5ea/doc/_build/html/_images/calibration_network.png
swmm5ea/doc/_build/html/_images/calibration_place_holder.png
swmm5ea/doc/_build/html/_images/calibration_project_parameters.png
swmm5ea/doc/_build/html/_images/epaswmm5.0.png
swmm5ea/doc/_build/html/_images/gui.png
