Metadata-Version: 1.1
Name: SWMM5-EA
Version: 5.1.0.103
Summary: SWMM5-EA
Home-page: http://assela.pathirana.net/SWMM5_EA
Author: Assela Pathirana
Author-email: assela@pathirana.net
License: License :: OSI Approved :: GNU General Public License v3 (GPLv3)
Download-URL: https://github.com/asselapathirana/swmm5-ea/releases
Keywords: EPA-SWMM,GA,Urban Drainage
Platform: UNKNOWN
Classifier: Programming Language :: Python
Classifier: Programming Language :: Python :: 2.7
Classifier: Environment :: Other Environment
Classifier: Intended Audience :: Education
Classifier: Intended Audience :: End Users/Desktop
Classifier: License :: OSI Approved :: GNU General Public License v3 (GPLv3)
Classifier: Operating System :: POSIX
Classifier: Operating System :: Microsoft :: Windows
Classifier: Topic :: Software Development :: Libraries :: Python Modules
Classifier: Development Status :: 4 - Beta
Classifier: Natural Language :: English
